myc_http_tools/__init__.py
myc_http_tools/__main__.py
myc_http_tools/__version__.py
myc_http_tools/exceptions.py
myc_http_tools/fastapi/__init__.py
myc_http_tools/fastapi/middleware.py
myc_http_tools/functions/__init__.py
myc_http_tools/functions/decode_and_decompress_profile_from_base64.py
myc_http_tools/models/__init__.py
myc_http_tools/models/licensed_resources.py
myc_http_tools/models/owner.py
myc_http_tools/models/permission.py
myc_http_tools/models/profile.py
myc_http_tools/models/related_accounts.py
myc_http_tools/models/tenants_ownership.py
myc_http_tools/models/verbose_status.py
myc_http_tools/settings.py
tests/__init__.py
tests/mock/__init__.py
tests/mock/large-profile-encoded.txt
tests/mock/large-profile.json
tests/test_decode_and_decompress_profile.py
tests/test_fastapi_integration.py
tests/test_licensed_resource.py
tests/test_licensed_resources.py
tests/test_permission.py
tests/test_profile.py
mycelium_http_tools-0.1.0a9.dist-info/METADATA
mycelium_http_tools-0.1.0a9.dist-info/WHEEL
mycelium_http_tools-0.1.0a9.dist-info/RECORD
