Metadata-Version: 2.4
Name: mycelium-http-tools
Version: 0.1.0a9
Summary: A python library to integrate python APIs in Mycelium API Gateway
License: Apache 2.0
Author: Samuel Galvão Elias
Author-email: sgelias@outlook.com
Requires-Python: >=3.12,<4.0
Classifier: License :: Other/Proprietary License
Classifier: Programming Language :: Python :: 3
Classifier: Programming Language :: Python :: 3.12
Classifier: Programming Language :: Python :: 3.13
Classifier: Programming Language :: Python :: 3.14
Provides-Extra: dev
Provides-Extra: fastapi
Requires-Dist: commitizen (>=4.9.1) ; extra == "dev"
Requires-Dist: fastapi[standard] (>=0.117.1,<0.118.0) ; extra == "fastapi"
Requires-Dist: mypy (>=1.18.2) ; extra == "dev"
Requires-Dist: pre-commit (>=4.3.0) ; extra == "dev"
Requires-Dist: pydantic (>=2.11.9,<3.0.0)
Requires-Dist: urllib3 (>=2.5.0,<3.0.0)
Requires-Dist: zstandard (>=0.25.0,<0.26.0) ; extra == "fastapi"
